odoo/addons/pos_order_to_sale_order_report/README.rst
odoo/addons/pos_order_to_sale_order_report/__init__.py
odoo/addons/pos_order_to_sale_order_report/__manifest__.py
odoo/addons/pos_order_to_sale_order_report/i18n/es.po
odoo/addons/pos_order_to_sale_order_report/i18n/it.po
odoo/addons/pos_order_to_sale_order_report/i18n/pos_order_to_sale_order_report.pot
odoo/addons/pos_order_to_sale_order_report/models/__init__.py
odoo/addons/pos_order_to_sale_order_report/models/pos_config.py
odoo/addons/pos_order_to_sale_order_report/models/res_config_settings.py
odoo/addons/pos_order_to_sale_order_report/readme/CONFIGURE.rst
odoo/addons/pos_order_to_sale_order_report/readme/CONTRIBUTORS.rst
odoo/addons/pos_order_to_sale_order_report/readme/DESCRIPTION.rst
odoo/addons/pos_order_to_sale_order_report/readme/USAGE.rst
odoo/addons/pos_order_to_sale_order_report/static/description/icon.png
odoo/addons/pos_order_to_sale_order_report/static/description/index.html
odoo/addons/pos_order_to_sale_order_report/static/img/pos_config.png
odoo/addons/pos_order_to_sale_order_report/static/src/js/Popups/CreateOrderPopup.esm.js
odoo/addons/pos_order_to_sale_order_report/views/res_config_settings_view.xml
odoo_addon_pos_order_to_sale_order_report-16.0.1.0.2.2.dist-info/METADATA
odoo_addon_pos_order_to_sale_order_report-16.0.1.0.2.2.dist-info/WHEEL
odoo_addon_pos_order_to_sale_order_report-16.0.1.0.2.2.dist-info/top_level.txt
odoo_addon_pos_order_to_sale_order_report-16.0.1.0.2.2.dist-info/RECORD
